Metadata-Version: 2.1
Name: exercice-pypi
Version: 0.1
Summary: Gaussian and Binominal distributions
Author: Karima Bouricha
